LICENSE
MANIFEST.in
README.rst
build.py
genattrs.py
genencodings.py
gentags.py
run_tests.py
setup.cfg
setup.py
win-ci.py
gumbo/attribute.c
gumbo/attribute.h
gumbo/char_ref.c
gumbo/char_ref.h
gumbo/char_ref.rl
gumbo/error.c
gumbo/error.h
gumbo/gumbo.h
gumbo/gumbo_edit.c
gumbo/gumbo_edit.h
gumbo/insertion_mode.h
gumbo/parser.c
gumbo/parser.h
gumbo/replacement.h
gumbo/string_buffer.c
gumbo/string_buffer.h
gumbo/string_piece.c
gumbo/string_piece.h
gumbo/svg_attrs.c
gumbo/svg_tags.c
gumbo/tag.c
gumbo/tag_enum.h
gumbo/tag_perf.h
gumbo/tag_sizes.h
gumbo/tag_strings.h
gumbo/token_type.h
gumbo/tokenizer.c
gumbo/tokenizer.h
gumbo/tokenizer_states.h
gumbo/utf8.c
gumbo/utf8.h
gumbo/util.c
gumbo/util.h
gumbo/vector.c
gumbo/vector.h
src/as-libxml.c
src/as-libxml.h
src/as-python-tree.c
src/as-python-tree.h
src/attr_enum.h
src/attr_perf.h
src/attr_sizes.h
src/attr_strings.h
src/data-types.h
src/python-wrapper.c
src/stack.h
src/html5_parser/__init__.py
src/html5_parser/dom.py
src/html5_parser/encoding_names.py
src/html5_parser/encoding_parser.py
src/html5_parser/soup.py
src/html5_parser/stdlib_etree.py
src/html5_parser.egg-info/PKG-INFO
src/html5_parser.egg-info/SOURCES.txt
src/html5_parser.egg-info/dependency_links.txt
src/html5_parser.egg-info/requires.txt
src/html5_parser.egg-info/top_level.txt
test/__init__.py
test/adapt.py
test/basic.py
test/html5lib_adapter.py
test/malformed.py
test/namespace.py
test/soup.py